[
    {
        "numero": "1",
        "nome": "LNA_IN",
        "tipo": "analog",
        "funcoes": ["Entrada e saída dos sinais de RF (Wi-Fi e Bluetooth) para a antena"],
        "categorias": ["Antena"],
        "avisos": ["Consulte o item 2.4 do datasheet para mais detalhes sobre pinos analógicos"]
    },
    {
        "numero": "2",
        "nome": "VDD3P3",
        "tipo": "power",
        "funcoes": ["Entrada de alimentação do domínio analógico"],
        "categorias": ["Power"],
        "avisos": [
            "Tensão Recomendada: 3.3V",
            "Tensão Mínima Recomendada: 3.0V",
            "Tensão Máxima Recomendada: 3.6V",
			"Consulte o item 2.5 do datasheet para mais detalhes sobre a alimentação do chip"
        ]
    },
    {
        "numero": "3",
        "nome": "VDD3P3",
        "tipo": "power",
        "funcoes": ["Entrada de alimentação do domínio analógico"],
        "categorias": ["Power"],
        "avisos": [
            "Tensão Recomendada: 3.3V",
            "Tensão Mínima Recomendada: 3.0V",
            "Tensão Máxima Recomendada: 3.6V",
			"Consulte o item 2.5 do datasheet para mais detalhes sobre a alimentação do chip"
        ]
    },
    {
        "numero": "4",
        "nome": "XTAL_32K_P",
        "tipo": "io",
        "alimentacao": ["VDD3P3_RTC"],
        "funcoes": [
            "GPIO0",
            "XTAL_32K_P",
            "ADC1_CH0"
        ],
        "categorias": [
            "GPIO",
            "Clock",
            "ADC"
        ]
    },
    {
        "numero": "5",
        "nome": "XTAL_32K_N",
        "tipo": "io",
        "alimentacao": ["VDD3P3_RTC"],
        "funcoes": [
            "GPIO1",
            "XTAL_32K_N",
            "ADC1_CH1"
        ],
        "categorias": [
            "GPIO",
            "Clock",
            "ADC"
        ]
    },
    {
        "numero": "6",
        "nome": "GPIO2",
        "tipo": "io",
        "alimentacao": ["VDD3P3_RTC"],
        "funcoes": [
            "GPIO2",
            "ADC1_CH2",
            "FSPIQ"
        ],
        "categorias": [
            "GPIO",
            "ADC",
            "SPI",
            "Strapping"
        ],
        "avisos": [
            "Durante o reset, este pino estará configurado como entrada",
            "Após o reset, este pino estará configurado como entrada",
            "Na verdade, esse pino não determina o modo de boot, mas é recomendado conectar ele com um pull-up para evitar glitches (consulte o item 3.1 do datasheet para mais detalhes)"
        ]
    },
    {
        "numero": "7",
        "nome": "CHIP_EN",
        "tipo": "analog",
        "funcoes": ["Habilitar o chip"],
        "categorias": ["Power"],
        "avisos": [
            "Colocar este pino em nível alto habilitará o funcionamento do chip",
            "Colocar este pino em nível baixo desabilitará o funcionamento do chip",
            "Não deixe este pino flutuando, utilize um resistor de pull-up externo"
        ]
    },
    {
        "numero": "8",
        "nome": "GPIO3",
        "tipo": "io",
        "alimentacao": ["VDD3P3_RTC"],
        "funcoes": [
            "GPIO3",
            "ADC1_CH3"
        ],
        "categorias": [
            "GPIO",
            "ADC"
        ],
        "avisos": [
            "Durante o reset, este pino estará configurado como entrada",
            "Após o reset, este pino estará configurado como entrada"
        ]
    },
    {
        "numero": "9",
        "nome": "MTMS",
        "tipo": "io",
        "alimentacao": ["VDD3P3_RTC"],
        "funcoes": [
            "GPIO4",
            "ADC1_CH4",
            "FSPIHD",
            "MTMS"
        ],
        "categorias": [
            "GPIO",
            "ADC",
            "SPI",
            "JTAG"
        ],
        "avisos": [
            "Após o reset, este pino estará configurado como entrada",
            "Pino utilizado para debugging"
        ]
    },
    {
        "numero": "10",
        "nome": "MTDI",
        "tipo": "io",
        "alimentacao": ["VDD3P3_RTC"],
        "funcoes": [
            "GPIO5",
            "ADC2_CH0",
            "FSPIWP",
            "MTDI"
        ],
        "categorias": [
            "GPIO",
            "ADC",
            "SPI",
            "JTAG"
        ],
        "avisos": [
            "Após o reset, este pino estará configurado como entrada",
            "Pino utilizado para debugging"
        ]
    },
    {
        "numero": "11",
        "nome": "VDD3P3_RTC",
        "tipo": "power",
        "funcoes": ["Entrada de alimentação do domínio de baixo consumo e parte do domínio digital"],
        "categorias": ["Power"],
        "avisos": [
            "Tensão Recomendada: 3.3V",
            "Tensão Mínima Recomendada: 3.0V",
            "Tensão Máxima Recomendada: 3.6V",
			"Consulte o item 2.5 do datasheet para mais detalhes sobre a alimentação do chip"
        ]
    },
    {
        "numero": "12",
        "nome": "MTCK",
        "tipo": "io",
        "alimentacao": ["VDD3P3_CPU"],
        "funcoes": [
            "GPIO6",
            "FSPICLK",
            "MTCK"
        ],
        "categorias": [
            "GPIO",
            "SPI",
            "JTAG"
        ],
        "avisos": [
            "Após o reset, este pino estará configurado como entrada",
            "Pino utilizado para debugging"
        ]
    },
    {
        "numero": "13",
        "nome": "MTDO",
        "tipo": "io",
        "alimentacao": ["VDD3P3_CPU"],
        "funcoes": [
            "GPIO7",
            "FSPID",
            "MTDO"
        ],
        "categorias": [
            "GPIO",
            "SPI",
            "JTAG"
        ],
        "avisos": [
            "Após o reset, este pino estará configurado como entrada",
            "Pino utilizado para debugging"
        ]
    },
    {
        "numero": "14",
        "nome": "GPIO8",
        "tipo": "io",
        "alimentacao": ["VDD3P3_CPU"],
        "funcoes": ["GPIO8"],
        "categorias": [
            "GPIO",
            "Strapping"
        ],
        "avisos": [
            "Durante o reset, este pino estará configurado como entrada",
            "Após o reset, este pino estará configurado como entrada",
            "Utilizado para controlar o modo de boot do chip (consulte o item 3.1 do datasheet para mais detalhes)"
        ]
    },
    {
        "numero": "15",
        "nome": "GPIO9",
        "tipo": "io",
        "alimentacao": ["VDD3P3_CPU"],
        "funcoes": ["GPIO9"],
        "categorias": [
            "GPIO",
            "Strapping"
        ],
        "avisos": [
            "Durante o reset, este pino estará configurado como entrada com o pull-up interno ativado",
            "Após o reset, este pino estará configurado como entrada com o pull-up interno ativado",
            "Utilizado para controlar o modo de boot do chip (consulte o item 3.1 do datasheet para mais detalhes)"
        ]
    },
    {
        "numero": "16",
        "nome": "GPIO10",
        "tipo": "io",
        "alimentacao": ["VDD3P3_CPU"],
        "funcoes": [
            "GPIO10",
            "FSPICS0"
        ],
        "categorias": [
            "GPIO",
            "SPI"
        ],
        "avisos": ["Após o reset, este pino estará configurado como entrada"]
    },
    {
        "numero": "17",
        "nome": "VDD3P3_CPU",
        "tipo": "power",
        "funcoes": ["Entrada de alimentação do domínio digital"],
        "categorias": ["Power"],
        "avisos": [
            "Tensão Recomendada: 3.3V",
            "Tensão Mínima Recomendada: 3.0V",
            "Tensão Máxima Recomendada: 3.6V",
			"Consulte o item 2.5 do datasheet para mais detalhes sobre a alimentação do chip"
        ]
    },
    {
        "numero": "18",
        "nome": "VDD_SPI",
        "tipo": "power",
        "alimentacao": ["VDD3P3_CPU"],
        "funcoes": [
            "Entrada/saída da alimentação da flash interna/externa",
            "GPIO11"
        ],
        "categorias": [
            "Power",
            "GPIO"
        ],
        "avisos": [
            "Tensão Recomendada: 3.3V",
            "Tensão Mínima Recomendada: 3.0V",
            "Tensão Máxima Recomendada: 3.6V",
			"Consulte o item 2.5 do datasheet para mais detalhes sobre a alimentação do chip",
            "Só pode ser utilizado como GPIO se a memória flash estiver sendo alimentada por uma fonte externa"
        ]
    },
    {
        "numero": "19",
        "nome": "SPIHD",
        "tipo": "io",
        "alimentacao": ["VDD_SPI", "VDD3P3_CPU"],
        "funcoes": [
            "GPIO12",
            "SPIHD"
        ],
        "categorias": [
            "GPIO",
            "SPI"
        ],
		"avisos": [
            "Durante o reset, este pino estará com o pull-up interno ativado",
            "Após o reset, este pino estará configurado como entrada com o pull-up interno ativado",
            "Utilizado pela memória flash SPI",
            "Não é recomendado utilizar este pino como GPIO"
        ]
    },
    {
        "numero": "20",
        "nome": "SPIWP",
        "tipo": "io",
        "alimentacao": ["VDD_SPI", "VDD3P3_CPU"],
        "funcoes": [
            "GPIO13",
            "SPIWP"
        ],
        "categorias": [
            "GPIO",
            "SPI"
        ],
		"avisos": [
            "Durante o reset, este pino estará com o pull-up interno ativado",
            "Após o reset, este pino estará configurado como entrada com o pull-up interno ativado",
            "Utilizado pela memória flash SPI",
            "Não é recomendado utilizar este pino como GPIO"
        ]
    },
    {
        "numero": "21",
        "nome": "SPICS0",
        "tipo": "io",
        "alimentacao": ["VDD_SPI", "VDD3P3_CPU"],
        "funcoes": [
            "GPIO14",
            "SPICS0"
        ],
        "categorias": [
            "GPIO",
            "SPI"
        ],
		"avisos": [
            "Durante o reset, este pino estará com o pull-up interno ativado",
            "Após o reset, este pino estará configurado como entrada com o pull-up interno ativado",
            "Utilizado pela memória flash SPI",
            "Não é recomendado utilizar este pino como GPIO"
        ]
    },
    {
        "numero": "22",
        "nome": "SPICLK",
        "tipo": "io",
        "alimentacao": ["VDD_SPI", "VDD3P3_CPU"],
        "funcoes": [
            "GPIO15",
            "SPICLK"
        ],
        "categorias": [
            "GPIO",
            "SPI"
        ],
        "avisos": [
            "Durante o reset, este pino estará com o pull-up interno ativado",
            "Após o reset, este pino estará configurado como entrada com o pull-up interno ativado",
            "Utilizado pela memória flash SPI",
            "Não é recomendado utilizar este pino como GPIO"
        ]
    },
    {
        "numero": "23",
        "nome": "SPID",
        "tipo": "io",
        "alimentacao": ["VDD_SPI", "VDD3P3_CPU"],
        "funcoes": [
            "GPIO16",
            "SPID"
        ],
        "categorias": [
            "GPIO",
            "SPI"
        ],
        "avisos": [
            "Durante o reset, este pino estará com o pull-up interno ativado",
            "Após o reset, este pino estará configurado como entrada com o pull-up interno ativado",
            "Utilizado pela memória flash SPI",
            "Não é recomendado utilizar este pino como GPIO"
        ]
    },
    {
        "numero": "24",
        "nome": "SPIQ",
        "tipo": "io",
        "alimentacao": ["VDD_SPI", "VDD3P3_CPU"],
        "funcoes": [
            "GPIO17",
            "SPIQ"
        ],
        "categorias": [
            "GPIO",
            "SPI"
        ],
        "avisos": [
            "Durante o reset, este pino estará com o pull-up interno ativado",
            "Após o reset, este pino estará configurado como entrada com o pull-up interno ativado",
            "Utilizado pela memória flash SPI",
            "Não é recomendado utilizar este pino como GPIO"
        ]
    },
    {
        "numero": "25",
        "nome": "GPIO18",
        "tipo": "io",
        "alimentacao": ["VDD3P3_CPU"],
        "funcoes": [
            "GPIO18",
            "USB_D-"
        ],
        "categorias": [
            "GPIO",
            "USB"
        ],
		"avisos": ["Por padrão, este pino é utilizado para USB Serial/JTAG"]
    },
    {
        "numero": "26",
        "nome": "GPIO19",
        "tipo": "io",
        "alimentacao": ["VDD3P3_CPU"],
        "funcoes": [
            "GPIO19",
            "USB_D+"
        ],
        "categorias": [
            "GPIO",
            "USB"
        ],
		"avisos": ["Por padrão, este pino é utilizado para USB Serial/JTAG"]
    },
    {
        "numero": "27",
        "nome": "U0RXD",
        "tipo": "io",
        "alimentacao": ["VDD3P3_CPU"],
        "funcoes": [
            "GPIO20",
            "U0RXD"
        ],
        "categorias": [
            "GPIO",
            "UART"
        ],
		"avisos": [
            "Após o reset, este pino estará configurado como entrada com o pull-up interno ativado",
            "Pino utilizado para debugging"
        ]
    },
    {
        "numero": "28",
        "nome": "U0TXD",
        "tipo": "io",
        "alimentacao": ["VDD3P3_CPU"],
        "funcoes": [
            "GPIO21",
            "U0TXD"
        ],
        "categorias": [
            "GPIO",
            "UART"
        ],
		"avisos": [
            "Após o reset, este pino estará com o pull-up interno ativado",
            "Pino utilizado para debugging"
        ]
    },
    {
        "numero": "29",
        "nome": "XTAL_N",
        "tipo": "analog",
        "funcoes": ["Entrada/Saída negativa de clock"],
        "categorias": ["Clock"],
        "avisos": ["Consulte o item 2.3.2 do datasheet para mais detalhes sobre pinos analógicos"]
    },
    {
        "numero": "30",
        "nome": "XTAL_P",
        "tipo": "analog",
        "funcoes": ["Entrada/Saída positiva de clock"],
        "categorias": ["Clock"],
        "avisos": ["Consulte o item 2.3.2 do datasheet para mais detalhes sobre pinos analógicos"]
    },
    {
        "numero": "31",
        "nome": "VDDA",
        "tipo": "power",
        "funcoes": ["Entrada de alimentação do domínio analógico"],
        "categorias": ["Power"],
        "avisos": [
            "Tensão Recomendada: 3.3V",
            "Tensão Mínima Recomendada: 3.0V",
            "Tensão Máxima Recomendada: 3.6V",
			"Consulte o item 2.5 do datasheet para mais detalhes sobre a alimentação do chip"
        ]
    },
    {
        "numero": "32",
        "nome": "VDDA",
        "tipo": "power",
        "funcoes": ["Entrada de alimentação do domínio analógico"],
        "categorias": ["Power"],
        "avisos": [
            "Tensão Recomendada: 3.3V",
            "Tensão Mínima Recomendada: 3.0V",
            "Tensão Máxima Recomendada: 3.6V",
			"Consulte o item 2.5 do datasheet para mais detalhes sobre a alimentação do chip"
        ]
    },
    {
        "numero": "33",
        "nome": "GND",
        "tipo": "ground",
        "funcoes": ["Referência elétrica do circuito (terra)"],
        "categorias": ["GND"]
    }
]